ihextools/__init__.py
ihextools/ihex.py
ihextools-1.2.0.dist-info/DESCRIPTION.rst
ihextools-1.2.0.dist-info/METADATA
ihextools-1.2.0.dist-info/RECORD
ihextools-1.2.0.dist-info/WHEEL
ihextools-1.2.0.dist-info/metadata.json
ihextools-1.2.0.dist-info/top_level.txt
