Metadata-Version: 2.0
Name: ihextools
Version: 1.2.0
Summary: Simple Intel hex library
Home-page: https://github.com/keyme/ihextools
Author: Jeff Ciesielski
Author-email: jeff.ciesielski@key.me
License: MIT
Keywords: ihex
Platform: UNKNOWN
Classifier: Development Status :: 4 - Beta
Classifier: Topic :: Utilities
Classifier: License :: OSI Approved :: MIT License
